py3dic/__init__.py
py3dic/common/__init__.py
py3dic/common/constants.py
py3dic/common/frame_range_parser.py
py3dic/dic/__init__.py
py3dic/dic/batch_dic_strain_processor.py
py3dic/dic/batch_image_marker_tracker.py
py3dic/dic/dic_grid_with_plots.py
py3dic/dic/io_utils.py
py3dic/dic/merge_dic_ut.py
py3dic/dic/_obsolete/__init__.py
py3dic/dic/_obsolete/_old_dic_grid.py
py3dic/dic/_obsolete/_old_pydic.py
py3dic/dic/_obsolete/draw_opencv_v2.py
py3dic/dic/_obsolete/pydic_merge_dic_ut.py
py3dic/dic/core/__init__.py
py3dic/dic/core/calc_grid_interpolator.py
py3dic/dic/core/calc_strain_calculator.py
py3dic/dic/core/compute_disp_array.py
py3dic/dic/core/core_calcs.py
py3dic/dic/core/dic_enums.py
py3dic/dic/core/dic_grid.py
py3dic/dic/core/dic_result_loader.py
py3dic/dic/core/grid_size.py
py3dic/dic/gui_selectors/__init__.py
py3dic/dic/gui_selectors/cv2_area_selector.py
py3dic/dic/gui_selectors/time_offset_selector.py
py3dic/dic/plotting/__init__.py
py3dic/dic/plotting/dic2d_contour_plot.py
py3dic/dic/plotting/dic_grid_plotter.py
py3dic/dic/rolling_processing/__init__.py
py3dic/dic/rolling_processing/rolling_dic_strain_processor.py
py3dic/dic/rolling_processing/rolling_image_marker_tracker.py
py3dic/dic/viewer/__init__.py
py3dic/dic/viewer/analysis_viewer.py
py3dic/guis/__init__.py
py3dic/guis/common/__init__.py
py3dic/guis/tk_dic_analysis/__init__.py
py3dic/guis/tk_dic_analysis/mvc_controller_dic.py
py3dic/guis/tk_dic_analysis/mvc_model_dic.py
py3dic/guis/tk_dic_analysis/mvc_view_dic.py
py3dic/guis/tk_dic_analysis/tk_dic_analysis_launcher.py
py3dic/guis/tk_dic_analysis/support/__init__.py
py3dic/guis/tk_dic_analysis/support/tkf_dic_parameters.py
py3dic/guis/tk_dic_analysis/support/tktl_roi_image_window.py
py3dic/guis/tk_dic_analysis/support/tktp_browse_results.py
py3dic/guis/tk_gen_strainmaps/__init__.py
py3dic/guis/tk_gen_strainmaps/__main__.py
py3dic/guis/tk_gen_strainmaps/controller.py
py3dic/guis/tk_gen_strainmaps/model.py
py3dic/guis/tk_gen_strainmaps/view.py
py3dic-0.5.0.dist-info/METADATA
py3dic-0.5.0.dist-info/WHEEL
py3dic-0.5.0.dist-info/entry_points.txt
py3dic-0.5.0.dist-info/top_level.txt
py3dic-0.5.0.dist-info/RECORD
