Metadata-Version: 2.4
Name: py3dic
Version: 0.5.0
Summary: A package for Digital Image Correlation (DIC) analysis in Python 3.
Author-email: "N. Papadakis" <npapnet@gmail.com>
Project-URL: Documentation, https://npapnet.github.io/py3dic/
Project-URL: Source, https://github.com/npapnet/py3dic
Classifier: Programming Language :: Python :: 3
Classifier: License :: OSI Approved :: MIT License
Classifier: Operating System :: OS Independent
Requires-Python: >=3.10
Requires-Dist: scipy
Requires-Dist: numpy
Requires-Dist: matplotlib
Requires-Dist: seaborn
Requires-Dist: pandas
Requires-Dist: openpyxl
Requires-Dist: ipykernel
Requires-Dist: jupyter
Requires-Dist: tqdm
Requires-Dist: opencv-python
Provides-Extra: test
Requires-Dist: pytest; extra == "test"
